modules/ramDmaCi/verilog/ramDmaCi.v
module ramDmaCi #( parameter [7:0] customId = 8'h00 )
                ( input wire        start,
                                   clock,
                                   reset,
                  input wire [31:0] valueA,
                                   valueB,
                  input wire [7:0]  ciN,
                  output wire       done,
                  output wire [31:0] result );

    wire [31:0] memDataOut;
    wire s_validCi     = (ciN == customId) && (start == 1'b1);
    wire s_validAccess = (valueA[31:10] == 22'b0);
    wire s_doOperation = s_validCi && s_validAccess;


    dualPortSSRAM #( .bitwidth(32), .nrOfEntries(512), .readAfterWrite(0) )
    mem ( .clockA(clock), .clockB(~clock), 
          .writeEnableA(valueA[9] && s_doOperation), .writeEnableB(1'b0), 
          .addressA(valueA[8:0]), .addressB(9'b0),
          .dataInA(valueB), .dataInB(32'b0),
          .dataOutA(memDataOut), .dataOutB());

    reg s_done, s_readPending;
    reg [31:0] s_result;

    assign done   = s_done;
    assign result = s_result;

    always @(posedge clock)
      begin
        if (reset) begin
          s_done        <= 1'b0;
          s_result      <= 32'b0;
          s_readPending <= 1'b0;
        end else begin
          s_done <= 1'b0;

          if (s_doOperation && valueA[9]) begin
            s_done <= 1'b1;                  // write: 1 cycle
          end else if (s_doOperation && !valueA[9]) begin
            s_readPending <= 1'b1;           // read: flag first cycle
          end

          if (s_readPending) begin
            s_result      <= memDataOut;     // capture after 2nd cycle
            s_done        <= 1'b1;
            s_readPending <= 1'b0;
          end
        end
      end


          

endmodule

module dualPortSSRAM #( parameter bitwidth = 32,
                        parameter nrOfEntries = 512,
                        parameter readAfterWrite = 0 )
                      ( input wire                          clockA, clockB,
                                                            writeEnableA, writeEnableB,
                        input wire [$clog2(nrOfEntries)-1:0] addressA, addressB,
                        input wire [bitwidth-1:0]            dataInA, dataInB,
                        output reg [bitwidth-1:0]            dataOutA, dataOutB );

  reg [bitwidth-1:0] memoryContent [nrOfEntries-1:0];

  always @(posedge clockA)
    begin
      if (readAfterWrite != 0) dataOutA = memoryContent[addressA];
      if (writeEnableA == 1'b1) memoryContent[addressA] = dataInA;
      if (readAfterWrite == 0) dataOutA = memoryContent[addressA];
    end

  always @(posedge clockB)
    begin
      if (readAfterWrite != 0) dataOutB = memoryContent[addressB];
      if (writeEnableB == 1'b1) memoryContent[addressB] = dataInB;
      if (readAfterWrite == 0) dataOutB = memoryContent[addressB];
    end

endmodule

modules/ramDmaCi/verilog/testbenchRamDma.v
`timescale 1ps/1ps

module ramDma_tb;

  reg        start, clock, reset;
  reg [31:0] valueA, valueB;
  reg [7:0]  ciN;
  wire       done;
  wire [31:0] result;

  ramDmaCi #(.customId(8'h00)) dut (
  
    .start(start), .clock(clock), .reset(reset),
    .valueA(valueA), .valueB(valueB),
    .ciN(ciN), .done(done), .result(result)
  );

  initial
    begin
      reset  = 1'b1;
      clock  = 1'b0;
      start  = 1'b0;
      ciN    = 8'h00;
      valueA = 32'b0;
      valueB = 32'b0;
      repeat (4) #5 clock = ~clock;
      reset = 1'b0;
      forever #5 clock = ~clock;
    end

  initial
    begin
      @(negedge reset);

      // write 0xDEADBEEF to address 5
      @(negedge clock);
      valueA = 32'h00000205; // bit9=1, addr=5
      valueB = 32'hDEADBEEF;
      start  = 1'b1;
      @(posedge done);
      @(negedge clock);
      start = 1'b0;

      // read back from address 5
      @(negedge clock);
      valueA = 32'h00000005; // bit9=0, addr=5
      valueB = 32'b0;
      start  = 1'b1;
      @(posedge done);
      @(negedge clock);
      start = 1'b0;
      $display("Read result: %h (expected DEADBEEF)", result);

      // write 0xCAFEBABE to address 0
      @(negedge clock);
      valueA = 32'h00000200; // bit9=1, addr=0
      valueB = 32'hCAFEBABE;
      start  = 1'b1;
      @(posedge done);
      @(negedge clock);
      start = 1'b0;

      // read back from address 0
      @(negedge clock);
      valueA = 32'h00000000;
      valueB = 32'b0;
      start  = 1'b1;
      @(posedge done);
      @(negedge clock);
      start = 1'b0;
      $display("Read result: %h (expected CAFEBABE)", result);

      $finish;
    end

  initial
    begin
      $dumpfile("ramDmaCiSignals.vcd");
      $dumpvars(1, dut);
    end

endmodule

modules/ramDmaCi/verilog/ramDmaCiSignals.vcd
$date
	Mon Apr 27 14:34:02 2026
$end
$version
	Icarus Verilog
$end
$timescale
	1ps
$end
$scope module ramDma_tb $end
$scope module dut $end
$var wire 8 ! ciN [7:0] $end
$var wire 1 " clock $end
$var wire 1 # done $end
$var wire 1 $ reset $end
$var wire 32 % result [31:0] $end
$var wire 1 & s_doOperation $end
$var wire 1 ' s_validCi $end
$var wire 1 ( start $end
$var wire 32 ) valueA [31:0] $end
$var wire 32 * valueB [31:0] $end
$var wire 1 + s_validAccess $end
$var wire 32 , memDataOut [31:0] $end
$var parameter 8 - customId $end
$var reg 1 . s_done $end
$var reg 1 / s_readPending $end
$var reg 32 0 s_result [31:0] $end
$upscope $end
$upscope $end
$enddefinitions $end
$comment Show the parameter values. $end
$dumpall
b0 -
$end
#0
$dumpvars
bx 0
x/
x.
bx ,
1+
b0 *
b0 )
0(
0'
0&
bx %
1$
x#
0"
b0 !
$end
#5
0/
b0 %
b0 0
0#
0.
1"
#10
0"
#15
1"
#20
0$
0"
#25
1"
#30
1&
1'
1(
b11011110101011011011111011101111 *
b1000000101 )
0"
#35
1#
1.
b11011110101011011011111011101111 ,
1"
#40
0&
0'
0(
0"
#45
0#
0.
1"
#50
1&
1'
1(
b0 *
b101 )
0"
#55
1/
1"
#60
0"
#65
0/
1#
1.
b11011110101011011011111011101111 %
b11011110101011011011111011101111 0
1"
#70
0&
0'
0(
0"
#75
0#
0.
1"
#80
1&
1'
1(
b11001010111111101011101010111110 *
b1000000000 )
0"
#85
1#
1.
b11001010111111101011101010111110 ,
1"
#90
0&
0'
0(
0"
#95
0#
0.
1"
#100
1&
1'
1(
b0 *
b0 )
0"
#105
1/
1"
#110
0"
#115
0/
1#
1.
b11001010111111101011101010111110 %
b11001010111111101011101010111110 0
1"
#120
0&
0'
0(
0"
